{"items": {}, "saving": 0.0, "price": 0.0, "savingText": "", "udoCat": [], "image": "", "percentage": 0.0, "min_purchase": 0, "tag": "branch", "name": "Coop", "children": [{"items": {}, "saving": 0.0, "price": 0.0, "savingText": "", "udoCat": [], "image": "", "percentage": 0.0, "min_purchase": 0, "tag": "branch", "name": "lebensmittel", "children": [{"items": {}, "saving": 0.0, "price": 0.0, "savingText": "", "udoCat": [], "image": "", "percentage": 0.0, "min_purchase": 0, "tag": "branch", "name": "fruechte-gemuese", "children": [{"items": {}, "saving": 0.0, "price": 0.0, "savingText": "", "udoCat": [], "image": "", "percentage": 0.0, "min_purchase": 0, "tag": "branch", "name": "fruechte", "children": [{"items": {}, "saving": 0.0, "price": 0.0, "savingText": "", "udoCat": [], "image": "", "percentage": 0.0, "min_purchase": 0, "tag": "branch", "name": "weitere-gartenfruechte"}, {"items": {}, "saving": 0.0, "price": 0.0, "savingText": "", "udoCat": [], "image": "", "percentage": 0.0, "min_purchase": 0, "tag": "branch", "name": "trauben-beeren", "children": [{"items": {}, "saving": 0.0, "price": 0.0, "savingText": "", "udoCat": [], "image": "", "percentage": 0.0, "min_purchase": 0, "tag": "branch", "name": "trauben"}, {"items": {}, "saving": 0.0, "price": 0.0, "savingText": "", "udoCat": [], "image": "", "percentage": 0.0, "min_purchase": 0, "tag": "branch", "name": "beeren"}]}, {"items": {}, "saving": 0.0, "price": 0.0, "savingText": "", "udoCat": [], "image": "", "percentage": 0.0, "min_purchase": 0, "tag": "branch", "name": "kiwis-melonen"}, {"items": {}, "saving": 0.0, "price": 0.0, "savingText": "", "udoCat": [], "image": "", "percentage": 0.0, "min_purchase": 0, "tag": "branch", "name": "aepfel-birnen"}]}, {"items": {}, "saving": 0.0, "price": 0.0, "savingText": "", "udoCat": [], "image": "", "percentage": 0.0, "min_purchase": 0, "tag": "branch", "name": "wurzelgemuese", "children": [{"items": {}, "saving": 0.0, "price": 0.0, "savingText": "", "udoCat": [], "image": "", "percentage": 0.0, "min_purchase": 0, "tag": "branch", "name": "kartoffeln"}]}, {"items": {}, "saving": 0.0, "price": 0.0, "savingText": "", "udoCat": [], "image": "", "percentage": 0.0, "min_purchase": 0, "tag": "branch", "name": "salatgemuese", "children": [{"items": {}, "saving": 0.0, "price": 0.0, "savingText": "", "udoCat": [], "image": "", "percentage": 0.0, "min_purchase": 0, "tag": "branch", "name": "tomaten"}]}]}, {"items": {}, "saving": 0.0, "price": 0.0, "savingText": "", "udoCat": [], "image": "", "percentage": 0.0, "min_purchase": 0, "tag": "branch", "name": "fleisch-fisch", "children": [{"items": {}, "saving": 0.0, "price": 0.0, "savingText": "", "udoCat": [], "image": "", "percentage": 0.0, "min_purchase": 0, "tag": "branch", "name": "abgepacktes-frischfleisch", "children": [{"items": {}, "saving": 0.0, "price": 0.0, "savingText": "", "udoCat": [], "image": "", "percentage": 0.0, "min_purchase": 0, "tag": "branch", "name": "gefluegel"}, {"items": {}, "saving": 0.0, "price": 0.0, "savingText": "", "udoCat": [], "image": "", "percentage": 0.0, "min_purchase": 0, "tag": "branch", "name": "schwein"}, {"items": {}, "saving": 0.0, "price": 0.0, "savingText": "", "udoCat": [], "image": "", "percentage": 0.0, "min_purchase": 0, "tag": "branch", "name": "hackfleisch"}, {"items": {}, "saving": 0.0, "price": 0.0, "savingText": "", "udoCat": [], "image": "", "percentage": 0.0, "min_purchase": 0, "tag": "branch", "name": "rind"}]}, {"items": {}, "saving": 0.0, "price": 0.0, "savingText": "", "udoCat": [], "image": "", "percentage": 0.0, "min_purchase": 0, "tag": "branch", "name": "abgepackter-fisch", "children": [{"items": {}, "saving": 0.0, "price": 0.0, "savingText": "", "udoCat": [], "image": "", "percentage": 0.0, "min_purchase": 0, "tag": "branch", "name": "geraeucherter-fisch"}]}, {"items": {}, "saving": 0.0, "price": 0.0, "savingText": "", "udoCat": [], "image": "", "percentage": 0.0, "min_purchase": 0, "tag": "branch", "name": "ihr-online-metzger"}]}, {"items": {}, "saving": 0.0, "price": 0.0, "savingText": "", "udoCat": [], "image": "", "percentage": 0.0, "min_purchase": 0, "tag": "branch", "name": "getraenke", "children": [{"items": {}, "saving": 0.0, "price": 0.0, "savingText": "", "udoCat": [], "image": "", "percentage": 0.0, "min_purchase": 0, "tag": "branch", "name": "bier", "children": [{"items": {}, "saving": 0.0, "price": 0.0, "savingText": "", "udoCat": [], "image": "", "percentage": 0.0, "min_purchase": 0, "tag": "branch", "name": "weizen", "children": [{"items": {}, "saving": 0.0, "price": 0.0, "savingText": "", "udoCat": [], "image": "", "percentage": 0.0, "min_purchase": 0, "tag": "branch", "name": "dosen"}]}, {"items": {}, "saving": 0.0, "price": 0.0, "savingText": "", "udoCat": [], "image": "", "percentage": 0.0, "min_purchase": 0, "tag": "branch", "name": "helles-bier-lager", "children": [{"items": {}, "saving": 0.0, "price": 0.0, "savingText": "", "udoCat": [], "image": "", "percentage": 0.0, "min_purchase": 0, "tag": "branch", "name": "flaschen"}, {"items": {}, "saving": 0.0, "price": 0.0, "savingText": "", "udoCat": [], "image": "", "percentage": 0.0, "min_purchase": 0, "tag": "branch", "name": "dosen"}]}, {"items": {}, "saving": 0.0, "price": 0.0, "savingText": "", "udoCat": [], "image": "", "percentage": 0.0, "min_purchase": 0, "tag": "branch", "name": "dunkles-bier", "children": [{"items": {}, "saving": 0.0, "price": 0.0, "savingText": "", "udoCat": [], "image": "", "percentage": 0.0, "min_purchase": 0, "tag": "branch", "name": "dosen"}]}, {"items": {}, "saving": 0.0, "price": 0.0, "savingText": "", "udoCat": [], "image": "", "percentage": 0.0, "min_purchase": 0, "tag": "branch", "name": "bier-mischgetraenke-cider"}]}, {"items": {}, "saving": 0.0, "price": 0.0, "savingText": "", "udoCat": [], "image": "", "percentage": 0.0, "min_purchase": 0, "tag": "branch", "name": "soft-drinks", "children": [{"items": {}, "saving": 0.0, "price": 0.0, "savingText": "", "udoCat": [], "image": "", "percentage": 0.0, "min_purchase": 0, "tag": "branch", "name": "multipacks-ab-1-liter"}, {"items": {}, "saving": 0.0, "price": 0.0, "savingText": "", "udoCat": [], "image": "", "percentage": 0.0, "min_purchase": 0, "tag": "branch", "name": "multipacks-unter-1-liter"}]}, {"items": {}, "saving": 0.0, "price": 0.0, "savingText": "", "udoCat": [], "image": "", "percentage": 0.0, "min_purchase": 0, "tag": "branch", "name": "mineralwasser", "children": [{"items": {}, "saving": 0.0, "price": 0.0, "savingText": "", "udoCat": [], "image": "", "percentage": 0.0, "min_purchase": 0, "tag": "branch", "name": "multipacks-ab-1-liter"}]}]}, {"items": {}, "saving": 0.0, "price": 0.0, "savingText": "", "udoCat": [], "image": "", "percentage": 0.0, "min_purchase": 0, "tag": "branch", "name": "milchprodukte-eier", "children": [{"items": {}, "saving": 0.0, "price": 0.0, "savingText": "", "udoCat": [], "image": "", "percentage": 0.0, "min_purchase": 0, "tag": "branch", "name": "abgepackter-kaese", "children": [{"items": {}, "saving": 0.0, "price": 0.0, "savingText": "", "udoCat": [], "image": "", "percentage": 0.0, "min_purchase": 0, "tag": "branch", "name": "frischkaese-mozzarella", "children": [{"items": {}, "saving": 0.0, "price": 0.0, "savingText": "", "udoCat": [], "image": "", "percentage": 0.0, "min_purchase": 0, "tag": "branch", "name": "mozzarella-ricotta"}, {"items": {}, "saving": 0.0, "price": 0.0, "savingText": "", "udoCat": [], "image": "", "percentage": 0.0, "min_purchase": 0, "tag": "branch", "name": "huettenkaese"}, {"items": {}, "saving": 0.0, "price": 0.0, "savingText": "", "udoCat": [], "image": "", "percentage": 0.0, "min_purchase": 0, "tag": "branch", "name": "frischkaese-aufstrich"}]}, {"items": {}, "saving": 0.0, "price": 0.0, "savingText": "", "udoCat": [], "image": "", "percentage": 0.0, "min_purchase": 0, "tag": "branch", "name": "weichkaese", "children": [{"items": {}, "saving": 0.0, "price": 0.0, "savingText": "", "udoCat": [], "image": "", "percentage": 0.0, "min_purchase": 0, "tag": "branch", "name": "weissschimmelkaese"}]}, {"items": {}, "saving": 0.0, "price": 0.0, "savingText": "", "udoCat": [], "image": "", "percentage": 0.0, "min_purchase": 0, "tag": "branch", "name": "hartkaese-halbhartkaese", "children": [{"items": {}, "saving": 0.0, "price": 0.0, "savingText": "", "udoCat": [], "image": "", "percentage": 0.0, "min_purchase": 0, "tag": "branch", "name": "sbrinz-parmesan-gruyere"}]}]}, {"items": {}, "saving": 0.0, "price": 0.0, "savingText": "", "udoCat": [], "image": "", "percentage": 0.0, "min_purchase": 0, "tag": "branch", "name": "butter-margarine", "children": [{"items": {}, "saving": 0.0, "price": 0.0, "savingText": "", "udoCat": [], "image": "", "percentage": 0.0, "min_purchase": 0, "tag": "branch", "name": "kochbutter-bratfett"}]}]}, {"items": {}, "saving": 0.0, "price": 0.0, "savingText": "", "udoCat": [], "image": "", "percentage": 0.0, "min_purchase": 0, "tag": "branch", "name": "vorraete", "children": [{"items": {}, "saving": 0.0, "price": 0.0, "savingText": "", "udoCat": [], "image": "", "percentage": 0.0, "min_purchase": 0, "tag": "branch", "name": "salatsaucen-kalte-saucen", "children": [{"items": {}, "saving": 0.0, "price": 0.0, "savingText": "", "udoCat": [], "image": "", "percentage": 0.0, "min_purchase": 0, "tag": "branch", "name": "mayonnaise"}]}, {"items": {}, "saving": 0.0, "price": 0.0, "savingText": "", "udoCat": [], "image": "", "percentage": 0.0, "min_purchase": 0, "tag": "branch", "name": "grundnahrungsmittel", "children": [{"items": {}, "saving": 0.0, "price": 0.0, "savingText": "", "udoCat": [], "image": "", "percentage": 0.0, "min_purchase": 0, "tag": "branch", "name": "mehl-zucker", "children": [{"items": {}, "saving": 0.0, "price": 0.0, "savingText": "", "udoCat": [], "image": "", "percentage": 0.0, "min_purchase": 0, "tag": "branch", "name": "mehl"}]}]}]}, {"items": {}, "saving": 0.0, "price": 0.0, "savingText": "", "udoCat": [], "image": "", "percentage": 0.0, "min_purchase": 0, "tag": "branch", "name": "suesses-snacks", "children": [{"items": {}, "saving": 0.0, "price": 0.0, "savingText": "", "udoCat": [], "image": "", "percentage": 0.0, "min_purchase": 0, "tag": "branch", "name": "chips-snacks", "children": [{"items": {}, "saving": 0.0, "price": 0.0, "savingText": "", "udoCat": [], "image": "", "percentage": 0.0, "min_purchase": 0, "tag": "branch", "name": "chips-popcorn", "children": [{"items": {}, "saving": 0.0, "price": 0.0, "savingText": "", "udoCat": [], "image": "", "percentage": 0.0, "min_purchase": 0, "tag": "branch", "name": "paprika-chili-chips"}, {"items": {}, "saving": 0.0, "price": 0.0, "savingText": "", "udoCat": [], "image": "", "percentage": 0.0, "min_purchase": 0, "tag": "branch", "name": "nature-chips"}]}]}, {"items": {}, "saving": 0.0, "price": 0.0, "savingText": "", "udoCat": [], "image": "", "percentage": 0.0, "min_purchase": 0, "tag": "branch", "name": "schokolade-suessigkeiten", "children": [{"items": {}, "saving": 0.0, "price": 0.0, "savingText": "", "udoCat": [], "image": "", "percentage": 0.0, "min_purchase": 0, "tag": "branch", "name": "tafelschokolade", "children": [{"items": {}, "saving": 0.0, "price": 0.0, "savingText": "", "udoCat": [], "image": "", "percentage": 0.0, "min_purchase": 0, "tag": "branch", "name": "milch"}]}]}]}, {"items": {}, "saving": 0.0, "price": 0.0, "savingText": "", "udoCat": [], "image": "", "percentage": 0.0, "min_purchase": 0, "tag": "branch", "name": "brot-backwaren", "children": [{"items": {}, "saving": 0.0, "price": 0.0, "savingText": "", "udoCat": [], "image": "", "percentage": 0.0, "min_purchase": 0, "tag": "branch", "name": "teig-tortenboden", "children": [{"items": {}, "saving": 0.0, "price": 0.0, "savingText": "", "udoCat": [], "image": "", "percentage": 0.0, "min_purchase": 0, "tag": "branch", "name": "kuchenteig"}]}, {"items": {}, "saving": 0.0, "price": 0.0, "savingText": "", "udoCat": [], "image": "", "percentage": 0.0, "min_purchase": 0, "tag": "branch", "name": "baeckerei"}, {"items": {}, "saving": 0.0, "price": 0.0, "savingText": "", "udoCat": [], "image": "", "percentage": 0.0, "min_purchase": 0, "tag": "branch", "name": "cracker-knaeckebrot", "children": [{"items": {}, "saving": 0.0, "price": 0.0, "savingText": "", "udoCat": [], "image": "", "percentage": 0.0, "min_purchase": 0, "tag": "branch", "name": "cracker", "children": [{"items": {}, "saving": 0.0, "price": 0.0, "savingText": "", "udoCat": [], "image": "", "percentage": 0.0, "min_purchase": 0, "tag": "branch", "name": "nature"}, {"items": {}, "saving": 0.0, "price": 0.0, "savingText": "", "udoCat": [], "image": "", "percentage": 0.0, "min_purchase": 0, "tag": "branch", "name": "gewuerzt"}, {"items": {}, "saving": 0.0, "price": 0.0, "savingText": "", "udoCat": [], "image": "", "percentage": 0.0, "min_purchase": 0, "tag": "branch", "name": "suess"}]}]}]}, {"items": {}, "saving": 0.0, "price": 0.0, "savingText": "", "udoCat": [], "image": "", "percentage": 0.0, "min_purchase": 0, "tag": "branch", "name": "tiefgekuehlt", "children": [{"items": {}, "saving": 0.0, "price": 0.0, "savingText": "", "udoCat": [], "image": "", "percentage": 0.0, "min_purchase": 0, "tag": "branch", "name": "fleisch-fisch", "children": [{"items": {}, "saving": 0.0, "price": 0.0, "savingText": "", "udoCat": [], "image": "", "percentage": 0.0, "min_purchase": 0, "tag": "branch", "name": "fleisch-gefluegel", "children": [{"items": {}, "saving": 0.0, "price": 0.0, "savingText": "", "udoCat": [], "image": "", "percentage": 0.0, "min_purchase": 0, "tag": "branch", "name": "fleischprodukte"}, {"items": {}, "saving": 0.0, "price": 0.0, "savingText": "", "udoCat": [], "image": "", "percentage": 0.0, "min_purchase": 0, "tag": "branch", "name": "fleisch-paniert"}]}, {"items": {}, "saving": 0.0, "price": 0.0, "savingText": "", "udoCat": [], "image": "", "percentage": 0.0, "min_purchase": 0, "tag": "branch", "name": "fisch-meeresfruechte", "children": [{"items": {}, "saving": 0.0, "price": 0.0, "savingText": "", "udoCat": [], "image": "", "percentage": 0.0, "min_purchase": 0, "tag": "branch", "name": "ganze-fische-filets"}]}]}, {"items": {}, "saving": 0.0, "price": 0.0, "savingText": "", "udoCat": [], "image": "", "percentage": 0.0, "min_purchase": 0, "tag": "branch", "name": "fertiggerichte", "children": [{"items": {}, "saving": 0.0, "price": 0.0, "savingText": "", "udoCat": [], "image": "", "percentage": 0.0, "min_purchase": 0, "tag": "branch", "name": "aperogebaeck"}]}]}]}, {"items": {}, "saving": 0.0, "price": 0.0, "savingText": "", "udoCat": [], "image": "", "percentage": 0.0, "min_purchase": 0, "tag": "branch", "name": "weine", "children": [{"items": {}, "saving": 0.0, "price": 0.0, "savingText": "", "udoCat": [], "image": "", "percentage": 0.0, "min_purchase": 0, "tag": "branch", "name": "wein-sortiment", "children": [{"items": {}, "saving": 0.0, "price": 0.0, "savingText": "", "udoCat": [], "image": "", "percentage": 0.0, "min_purchase": 0, "tag": "branch", "name": "weissweine"}, {"items": {}, "saving": 0.0, "price": 0.0, "savingText": "", "udoCat": [], "image": "", "percentage": 0.0, "min_purchase": 0, "tag": "branch", "name": "rotweine"}, {"items": {}, "saving": 0.0, "price": 0.0, "savingText": "", "udoCat": [], "image": "", "percentage": 0.0, "min_purchase": 0, "tag": "branch", "name": "roseweine"}, {"items": {}, "saving": 0.0, "price": 0.0, "savingText": "", "udoCat": [], "image": "", "percentage": 0.0, "min_purchase": 0, "tag": "branch", "name": "champagner"}, {"items": {}, "saving": 0.0, "price": 0.0, "savingText": "", "udoCat": [], "image": "", "percentage": 0.0, "min_purchase": 0, "tag": "branch", "name": "schaumweine", "children": [{"items": {}, "saving": 0.0, "price": 0.0, "savingText": "", "udoCat": [], "image": "", "percentage": 0.0, "min_purchase": 0, "tag": "branch", "name": "italien"}]}]}]}, {"items": {}, "saving": 0.0, "price": 0.0, "savingText": "", "udoCat": [], "image": "", "percentage": 0.0, "min_purchase": 0, "tag": "branch", "name": "aktionen", "children": [{"items": {}, "saving": 0.0, "price": 0.0, "savingText": "", "udoCat": [], "image": "", "percentage": 0.0, "min_purchase": 0, "tag": "branch", "name": "wochenaktionen", "children": [{"items": {}, "saving": 0.0, "price": 0.0, "savingText": "", "udoCat": [], "image": "", "percentage": 0.0, "min_purchase": 0, "tag": "branch", "name": "vorschau-aktionswoche"}]}]}, {"items": {}, "saving": 0.0, "price": 0.0, "savingText": "", "udoCat": [], "image": "", "percentage": 0.0, "min_purchase": 0, "tag": "branch", "name": "haushalt-tier", "children": [{"items": {}, "saving": 0.0, "price": 0.0, "savingText": "", "udoCat": [], "image": "", "percentage": 0.0, "min_purchase": 0, "tag": "branch", "name": "reinigung-putzen", "children": [{"items": {}, "saving": 0.0, "price": 0.0, "savingText": "", "udoCat": [], "image": "", "percentage": 0.0, "min_purchase": 0, "tag": "branch", "name": "kueche", "children": [{"items": {}, "saving": 0.0, "price": 0.0, "savingText": "", "udoCat": [], "image": "", "percentage": 0.0, "min_purchase": 0, "tag": "branch", "name": "abwaschmittel"}]}, {"items": {}, "saving": 0.0, "price": 0.0, "savingText": "", "udoCat": [], "image": "", "percentage": 0.0, "min_purchase": 0, "tag": "branch", "name": "schwaemme-lappen-buersten", "children": [{"items": {}, "saving": 0.0, "price": 0.0, "savingText": "", "udoCat": [], "image": "", "percentage": 0.0, "min_purchase": 0, "tag": "branch", "name": "bodenwischer-eimer"}, {"items": {}, "saving": 0.0, "price": 0.0, "savingText": "", "udoCat": [], "image": "", "percentage": 0.0, "min_purchase": 0, "tag": "branch", "name": "lappen"}, {"items": {}, "saving": 0.0, "price": 0.0, "savingText": "", "udoCat": [], "image": "", "percentage": 0.0, "min_purchase": 0, "tag": "branch", "name": "staubfaenger"}]}]}, {"items": {}, "saving": 0.0, "price": 0.0, "savingText": "", "udoCat": [], "image": "", "percentage": 0.0, "min_purchase": 0, "tag": "branch", "name": "tierwelt", "children": [{"items": {}, "saving": 0.0, "price": 0.0, "savingText": "", "udoCat": [], "image": "", "percentage": 0.0, "min_purchase": 0, "tag": "branch", "name": "katzen", "children": [{"items": {}, "saving": 0.0, "price": 0.0, "savingText": "", "udoCat": [], "image": "", "percentage": 0.0, "min_purchase": 0, "tag": "branch", "name": "katzenfutter", "children": [{"items": {}, "saving": 0.0, "price": 0.0, "savingText": "", "udoCat": [], "image": "", "percentage": 0.0, "min_purchase": 0, "tag": "branch", "name": "snacks-und-katzenmilch"}, {"items": {}, "saving": 0.0, "price": 0.0, "savingText": "", "udoCat": [], "image": "", "percentage": 0.0, "min_purchase": 0, "tag": "branch", "name": "nassfutter"}, {"items": {}, "saving": 0.0, "price": 0.0, "savingText": "", "udoCat": [], "image": "", "percentage": 0.0, "min_purchase": 0, "tag": "branch", "name": "trockenfutter"}]}]}]}]}, {"items": {}, "saving": 0.0, "price": 0.0, "savingText": "", "udoCat": [], "image": "", "percentage": 0.0, "min_purchase": 0, "tag": "branch", "name": "kosmetik-gesundheit", "children": [{"items": {}, "saving": 0.0, "price": 0.0, "savingText": "", "udoCat": [], "image": "", "percentage": 0.0, "min_purchase": 0, "tag": "branch", "name": "baby-kind", "children": [{"items": {}, "saving": 0.0, "price": 0.0, "savingText": "", "udoCat": [], "image": "", "percentage": 0.0, "min_purchase": 0, "tag": "branch", "name": "windeln", "children": [{"items": {}, "saving": 0.0, "price": 0.0, "savingText": "", "udoCat": [], "image": "", "percentage": 0.0, "min_purchase": 0, "tag": "branch", "name": "11-27kg"}, {"items": {}, "saving": 0.0, "price": 0.0, "savingText": "", "udoCat": [], "image": "", "percentage": 0.0, "min_purchase": 0, "tag": "branch", "name": "7-20kg"}]}]}, {"items": {}, "saving": 0.0, "price": 0.0, "savingText": "", "udoCat": [], "image": "", "percentage": 0.0, "min_purchase": 0, "tag": "branch", "name": "koerperpflege", "children": [{"items": {}, "saving": 0.0, "price": 0.0, "savingText": "", "udoCat": [], "image": "", "percentage": 0.0, "min_purchase": 0, "tag": "branch", "name": "seife", "children": [{"items": {}, "saving": 0.0, "price": 0.0, "savingText": "", "udoCat": [], "image": "", "percentage": 0.0, "min_purchase": 0, "tag": "branch", "name": "nachfuellbeutel"}]}]}, {"items": {}, "saving": 0.0, "price": 0.0, "savingText": "", "udoCat": [], "image": "", "percentage": 0.0, "min_purchase": 0, "tag": "branch", "name": "gesundheit-hausapotheke", "children": [{"items": {}, "saving": 0.0, "price": 0.0, "savingText": "", "udoCat": [], "image": "", "percentage": 0.0, "min_purchase": 0, "tag": "branch", "name": "hausapotheke", "children": [{"items": {}, "saving": 0.0, "price": 0.0, "savingText": "", "udoCat": [], "image": "", "percentage": 0.0, "min_purchase": 0, "tag": "branch", "name": "desinfektion-schutz"}]}]}, {"items": {}, "saving": 0.0, "price": 0.0, "savingText": "", "udoCat": [], "image": "", "percentage": 0.0, "min_purchase": 0, "tag": "branch", "name": "haarpflege-styling", "children": [{"items": {}, "saving": 0.0, "price": 0.0, "savingText": "", "udoCat": [], "image": "", "percentage": 0.0, "min_purchase": 0, "tag": "branch", "name": "shampoo", "children": [{"items": {}, "saving": 0.0, "price": 0.0, "savingText": "", "udoCat": [], "image": "", "percentage": 0.0, "min_purchase": 0, "tag": "branch", "name": "feuchtigkeits-shampoo"}]}]}, {"items": {}, "saving": 0.0, "price": 0.0, "savingText": "", "udoCat": [], "image": "", "percentage": 0.0, "min_purchase": 0, "tag": "branch", "name": "zahnpflege", "children": [{"items": {}, "saving": 0.0, "price": 0.0, "savingText": "", "udoCat": [], "image": "", "percentage": 0.0, "min_purchase": 0, "tag": "branch", "name": "zahnpaste", "children": [{"items": {}, "saving": 0.0, "price": 0.0, "savingText": "", "udoCat": [], "image": "", "percentage": 0.0, "min_purchase": 0, "tag": "branch", "name": "zahnpaste-fuer-erwachsene"}]}]}]}]}